JvTest
