Metadata-Version: 2.1
Name: JvTest
Version: 0.0.14
Summary: Apenas Testando
Home-page: UNKNOWN
Author: Jvsm Games
Author-email: jvsm5000wt@gmail.com
License: MIT License
Keywords: teste
Platform: UNKNOWN
License-File: LICENCE
